prompt_smart_menu/__init__.py
prompt_smart_menu/helpers.py
prompt_smart_menu/input_parser.py
prompt_smart_menu/smart_menu.py
prompt_smart_menu-0.1.dist-info/AUTHORS.rst
prompt_smart_menu-0.1.dist-info/LICENSE.txt
prompt_smart_menu-0.1.dist-info/METADATA
prompt_smart_menu-0.1.dist-info/WHEEL
prompt_smart_menu-0.1.dist-info/top_level.txt
prompt_smart_menu-0.1.dist-info/RECORD
