Metadata-Version: 2.1
Name: prompt-smart-menu
Version: 0.1
Summary: Library for building command line menus in Python
Home-page: https://github.com/future-cyborg/python-prompt-smart-menu/
Author: Yesha
Author-email: valetudinarygoat@gmail.com
License: mit
Project-URL: Documentation, https://python-prompt-smart-menu.readthedocs.io/en/latest/
Platform: any
Classifier: Development Status :: 2 - Pre-Alpha
Classifier: Environment :: Console
Classifier: Intended Audience :: Developers
Classifier: License :: OSI Approved :: MIT License
Classifier: Operating System :: OS Independent
Classifier: Programming Language :: Python :: 3
Classifier: Programming Language :: Python :: 3.6
Classifier: Programming Language :: Python :: 3.7
Classifier: Programming Language :: Python :: 3.8
Classifier: Programming Language :: Python :: 3 :: Only
Classifier: Programming Language :: Python
Classifier: Topic :: Software Development
Requires-Python: >=3.6
Provides-Extra: testing
Requires-Dist: pytest ; extra == 'testing'
Requires-Dist: pytest-cov ; extra == 'testing'
